{
  "beverage": [
    "neo_mystias_izakaya:beverages/mid_alcohol",
    "neo_mystias_izakaya:beverages/heatable",
    "neo_mystias_izakaya:beverages/bitter",
    "neo_mystias_izakaya:beverages/stimulating"
  ],
  "chats": [
    "neo_mystias_izakaya:customer/poker_soldier/chat_0",
    "neo_mystias_izakaya:customer/poker_soldier/chat_1",
    "neo_mystias_izakaya:customer/poker_soldier/chat_2",
    "neo_mystias_izakaya:customer/poker_soldier/chat_3"
  ],
  "dislikes": [],
  "likes": [
    "neo_mystias_izakaya:cuisines/homecooking",
    "neo_mystias_izakaya:cuisines/greasy",
    "neo_mystias_izakaya:cuisines/filling",
    "neo_mystias_izakaya:cuisines/salty",
    "neo_mystias_izakaya:cuisines/signature",
    "neo_mystias_izakaya:cuisines/refreshing",
    "neo_mystias_izakaya:cuisines/trend_popular"
  ],
  "locations": [
    "neo_mystias_izakaya:makai"
  ]
}