{
  "beverage": [
    "neo_mystias_izakaya:beverages/chillable",
    "neo_mystias_izakaya:beverages/fruity",
    "neo_mystias_izakaya:beverages/sweet"
  ],
  "budget": {
    "max": 200,
    "min": 100
  },
  "chats": [
    "neo_mystias_izakaya:customer/cirno/chat_0",
    "neo_mystias_izakaya:customer/cirno/chat_1",
    "neo_mystias_izakaya:customer/cirno/chat_2",
    "neo_mystias_izakaya:customer/cirno/chat_3",
    "neo_mystias_izakaya:customer/cirno/chat_4"
  ],
  "dislikes": [
    "neo_mystias_izakaya:cuisines/good_with_alcohol",
    "neo_mystias_izakaya:cuisines/cultural_heritage",
    "neo_mystias_izakaya:cuisines/expensive",
    "neo_mystias_izakaya:cuisines/trend_popular"
  ],
  "likes": [
    "neo_mystias_izakaya:cuisines/sweet",
    "neo_mystias_izakaya:cuisines/photogenic",
    "neo_mystias_izakaya:cuisines/refreshing",
    "neo_mystias_izakaya:cuisines/peculiar",
    "neo_mystias_izakaya:cuisines/trend_unpopular"
  ],
  "locations": [
    "neo_mystias_izakaya:scarlet_devil_mansion",
    "neo_mystias_izakaya:youkai_mountain"
  ],
  "spellCards": []
}